setup.py
distributions/Binomialdistribution.py
distributions/Gaussiandistribution.py
distributions/Generaldistribution.py
distributions/__init__.py
ngonar_distributions.egg-info/PKG-INFO
ngonar_distributions.egg-info/SOURCES.txt
ngonar_distributions.egg-info/dependency_links.txt
ngonar_distributions.egg-info/not-zip-safe
ngonar_distributions.egg-info/top_level.txt