Metadata-Version: 1.0
Name: ngonar-distributions
Version: 0.1
Summary: Gaussian ngonar distributions
Home-page: UNKNOWN
Author: UNKNOWN
Author-email: UNKNOWN
License: UNKNOWN
Platform: UNKNOWN
